vb_toolbox/__init__.py
vb_toolbox/app.py
vb_toolbox/app_gui.py
vb_toolbox/io.py
vb_toolbox/numerics.py
vb_toolbox/vb_index.py
vb_toolbox/vb_io.py
vb_toolbox/assets/vb_gui_icon.png
vb_toolbox-2.0.0.dist-info/LICENSE
vb_toolbox-2.0.0.dist-info/METADATA
vb_toolbox-2.0.0.dist-info/WHEEL
vb_toolbox-2.0.0.dist-info/entry_points.txt
vb_toolbox-2.0.0.dist-info/top_level.txt
vb_toolbox-2.0.0.dist-info/RECORD
